thr/__init__.py
thr/api.py
thr/crypto.py
thr/messages.py
thr/utils.py
thr-0.3.dist-info/LICENSE
thr-0.3.dist-info/METADATA
thr-0.3.dist-info/WHEEL
thr-0.3.dist-info/top_level.txt
thr-0.3.dist-info/RECORD
