Metadata-Version: 2.1
Name: thr
Version: 0.3
Summary: Minimal Threema Gateway library
Home-page: http://github.com/coffeemakr/python-thr
Author: coffeemakr
License: Unlicense
Platform: UNKNOWN
Classifier: Programming Language :: Python :: 3
Classifier: License :: Public Domain
Classifier: Operating System :: OS Independent
Requires-Python: >=3.6
